{
  "generated_at": "2026-07-20T07:00:50Z",
  "source": "tao.com Data API + taostats",
  "taostats_enabled": true,
  "tao": {
    "price_usd": 193.90601570645762,
    "change_24h_pct": -2.0659669717143245,
    "market_cap_usd": 2160580464.8027496
  },
  "network": {
    "total_subnets": 128,
    "staked_tao": 7437339.891416286,
    "staked_root_pct": 73.0289962482055,
    "staked_alpha_pct": 26.97100375179449
  },
  "subnet": {
    "netuid": 118,
    "name": "Ditto",
    "price_usd": 2.7509318405190064,
    "price_tao": 0.014191827,
    "market_cap_usd": 6899301.388794655,
    "fdv_usd": 57681000.04907597,
    "volume_24h_usd": 371907.9497592257,
    "change_24h_pct": -9.40079514011668,
    "change_7d_pct": -17.728402504931164,
    "change_30d_pct": -23.71470203869955,
    "tao_in_pool": 7465.937229128,
    "alpha_in_pool": 526072.982010669,
    "circulating_alpha": 2507987.0344926445,
    "total_traders": 3968,
    "holder_count": 2118,
    "rank": 21
  },
  "leaderboard": {
    "sn25_rank": 21,
    "total": 129,
    "rows": [
      {
        "rank": 18,
        "netuid": 53,
        "name": "engy",
        "mcap_usd": 16507977.527447395,
        "change_7d": 7.32872892733022,
        "is_sn25": false,
        "is_target": false
      },
      {
        "rank": 19,
        "netuid": 5,
        "name": "Hone",
        "mcap_usd": 14807455.664059263,
        "change_7d": -2.1297831509900074,
        "is_sn25": false,
        "is_target": false
      },
      {
        "rank": 20,
        "netuid": 28,
        "name": "gm",
        "mcap_usd": 15511562.147560539,
        "change_7d": 15.344334247608904,
        "is_sn25": false,
        "is_target": false
      },
      {
        "rank": 21,
        "netuid": 118,
        "name": "Ditto",
        "mcap_usd": 6897539.770009797,
        "change_7d": -17.728402504931164,
        "is_sn25": true,
        "is_target": false
      },
      {
        "rank": 22,
        "netuid": 91,
        "name": "cascade",
        "mcap_usd": 3265142.6739248754,
        "change_7d": -16.843592909479433,
        "is_sn25": false,
        "is_target": false
      },
      {
        "rank": 23,
        "netuid": 96,
        "name": "Verathos",
        "mcap_usd": 2280984.603705592,
        "change_7d": -21.993280310841595,
        "is_sn25": false,
        "is_target": false
      },
      {
        "rank": 24,
        "netuid": 114,
        "name": "SOMA",
        "mcap_usd": 4295992.5842071995,
        "change_7d": -4.8468624649792496,
        "is_sn25": false,
        "is_target": false
      }
    ]
  },
  "emissions": {
    "total": {
      "tao_day": 101.9957544,
      "usd_day": 19777.590354678392,
      "usd_year": 7218820.479457613
    },
    "owner": {
      "tao_day": 18.35876888536507,
      "usd_day": 3559.875727836825,
      "usd_year": 1299354.640660441
    },
    "miner": {
      "tao_day": 41.81849275731746,
      "usd_day": 8108.857313420784,
      "usd_year": 2959732.919398586
    },
    "validator": {
      "tao_day": 41.81849275731746,
      "usd_day": 8108.857313420784,
      "usd_year": 2959732.919398586
    },
    "incentive_burn_pct": 0.0
  },
  "conviction": {
    "available": true,
    "locked_alpha": 106538.379952273,
    "locked_usd": 293079.82164801954,
    "pct_of_circulating": 4.247963744909282,
    "lock_count": 5,
    "perpetual_count": 1,
    "top": [
      {
        "coldkey": "5GH2aUTMRUh1RprCgH4x3tRyCaKeUi5BfmYCfs1NARA8R54n",
        "alpha": 58230.568238532,
        "perpetual": true,
        "owner_hotkey": true,
        "label": "Const",
        "hl": "orange"
      },
      {
        "coldkey": "5HihiJi6XbPhnPBKGwHMYwNnCNjXZnvQ64VTqdY4tLvUmKAq",
        "alpha": 23201.745919838,
        "perpetual": false,
        "owner_hotkey": true,
        "label": null,
        "hl": null
      },
      {
        "coldkey": "5GU1RuZTnencf9ETjtStxSWrh5UyMUxpJDjy5Y74fCnvLCPJ",
        "alpha": 11574.196883692,
        "perpetual": false,
        "owner_hotkey": true,
        "label": null,
        "hl": null
      },
      {
        "coldkey": "5F9tvGHYMkoJ95biTvmscmnW6bxzXq5VUsGhX4q4fZvpu2sy",
        "alpha": 11572.746263278,
        "perpetual": false,
        "owner_hotkey": true,
        "label": null,
        "hl": null
      },
      {
        "coldkey": "5EHRQUR6wdnLYiNuZ6HdahkLzSgLMxFF8gz9gBBcg5gHieJi",
        "alpha": 1959.122646933,
        "perpetual": false,
        "owner_hotkey": true,
        "label": null,
        "hl": null
      }
    ],
    "stale": true
  },
  "validators": [
    {
      "name": "tao.bot",
      "hotkey": "5E2LP6EnZ54m3wS8s1yPvD5c3xo71kQroBw7aUVK32TKeZ5u",
      "stake_alpha": 405445.880733554,
      "dominance_pct": 51.39,
      "apr_pct": 49.53,
      "nominators": 381
    },
    {
      "name": "Ditto",
      "hotkey": "5HmP9732JFjnut2RY9yg4Gz2qJ38vF8xFwZb5dQVPF7FsmZz",
      "stake_alpha": 240140.753208786,
      "dominance_pct": 30.44,
      "apr_pct": 41.82,
      "nominators": 37
    },
    {
      "name": "TAO.com",
      "hotkey": "5FU3YKmvVry2EVRUqzcdaTRAqW1E6nqPPPqmUGLe25JBmNDd",
      "stake_alpha": 56053.869606949,
      "dominance_pct": 7.1,
      "apr_pct": 47.81,
      "nominators": 37
    },
    {
      "name": "Kooltek68",
      "hotkey": "5HdZvp9NTBtXYRi9WMvtS9hMjTWUiSbQhRvodGYXWzT11868",
      "stake_alpha": 35643.429779171,
      "dominance_pct": 4.51,
      "apr_pct": 5.5,
      "nominators": 13
    },
    {
      "name": "1T1B.AI",
      "hotkey": "5CaJhaYX7DaM3KujVzU6MFYmLX5vKstrspHpPPM4zbZGZC24",
      "stake_alpha": 22391.949460751,
      "dominance_pct": 2.83,
      "apr_pct": 37.6,
      "nominators": 19
    },
    {
      "name": "Rizzo (Insured)",
      "hotkey": "5CFtzzb4vym9eysfeF9cxxp6D7gksuUVTKYNq1mchnrMs118",
      "stake_alpha": 17453.402600508,
      "dominance_pct": 2.21,
      "apr_pct": 43.84,
      "nominators": 20
    },
    {
      "name": "MUV",
      "hotkey": "5DJA8FF1Zn9nin1eQCWE9N63Hav23MD86kQQ4gipep1sfMUV",
      "stake_alpha": 4282.586398732,
      "dominance_pct": 0.54,
      "apr_pct": 30.85,
      "nominators": 8
    },
    {
      "name": "Unnamed",
      "hotkey": "5CsvRJXuR955WojnGMdok1hbhffZyB4N5ocrv82f3p5A2zVp",
      "stake_alpha": 3884.005072755,
      "dominance_pct": 0.49,
      "apr_pct": 34.07,
      "nominators": 23
    },
    {
      "name": "K8STAKE.AI",
      "hotkey": "5EtUYRu7sFqs9obCrN6JSNTnAAcpk98oJ27YV2EF9gC4tvzs",
      "stake_alpha": 3215.557764912,
      "dominance_pct": 0.4,
      "apr_pct": 33.68,
      "nominators": 9
    },
    {
      "name": "Unnamed",
      "hotkey": "5HbScNssaEfioJHXjcXdpyqo1AKnYjymidGF8opcF9rTFZdT",
      "stake_alpha": 206.23810958,
      "dominance_pct": 0.02,
      "apr_pct": 32.31,
      "nominators": 2
    }
  ],
  "holders": [
    {
      "rank": 1,
      "coldkey": "5CJWxrvB764kK35knZdCity4p8ceNVSjt4j7jHAuKZVz35oV",
      "alpha": 96278.695978649,
      "usd": 264856.13033131475,
      "share_pct": 3.838883321744356,
      "label": null,
      "hl": null,
      "is_val": false,
      "entered": null,
      "entered_method": "baseline",
      "is_new": false
    },
    {
      "rank": 2,
      "coldkey": "5DeYByRJ76PNtrubYM5aUE4pxshVUKNLjiBc3KgvLkMVPtFh",
      "alpha": 65385.9904186,
      "usd": 179872.4029663974,
      "share_pct": 2.607110384517092,
      "label": null,
      "hl": null,
      "is_val": false,
      "entered": null,
      "entered_method": "baseline",
      "is_new": false
    },
    {
      "rank": 3,
      "coldkey": "5GH2aUTMRUh1RprCgH4x3tRyCaKeUi5BfmYCfs1NARA8R54n",
      "alpha": 63099.555898818,
      "usd": 173582.57744466732,
      "share_pct": 2.515944262510224,
      "label": "Const",
      "hl": "orange",
      "is_val": false,
      "entered": null,
      "entered_method": "baseline",
      "is_new": false
    },
    {
      "rank": 4,
      "coldkey": "5F3ATFoMzk88rkqujjrjSCRzVRQUTVrycUgr1etCVR8wHCZx",
      "alpha": 55707.405205593,
      "usd": 153247.27473276004,
      "share_pct": 2.2211998881749557,
      "label": null,
      "hl": null,
      "is_val": false,
      "entered": null,
      "entered_method": "baseline",
      "is_new": false
    },
    {
      "rank": 5,
      "coldkey": "5DUJfND9r2BjiJHNKSxJxzT7ptrxiseFe1GxeMwcTov52Y55",
      "alpha": 53472.00266901,
      "usd": 147097.8347184969,
      "share_pct": 2.1320685447573364,
      "label": "SN118 owner",
      "hl": "green",
      "is_val": true,
      "entered": null,
      "entered_method": "baseline",
      "is_new": false
    },
    {
      "rank": 6,
      "coldkey": "5F9tvGHYMkoJ95biTvmscmnW6bxzXq5VUsGhX4q4fZvpu2sy",
      "alpha": 46876.144373458,
      "usd": 128953.07811771148,
      "share_pct": 1.8690744301611133,
      "label": null,
      "hl": null,
      "is_val": false,
      "entered": null,
      "entered_method": "baseline",
      "is_new": false
    },
    {
      "rank": 7,
      "coldkey": "5GU1RuZTnencf9ETjtStxSWrh5UyMUxpJDjy5Y74fCnvLCPJ",
      "alpha": 46679.330890406,
      "usd": 128411.6576405403,
      "share_pct": 1.8612269620384636,
      "label": null,
      "hl": null,
      "is_val": false,
      "entered": null,
      "entered_method": "baseline",
      "is_new": false
    },
    {
      "rank": 8,
      "coldkey": "5D5VPCtwwHMDrGrbp66GH4KiHNczM4JKhMpXacGt5iPaZUtz",
      "alpha": 46677.314669563,
      "usd": 128406.11115442576,
      "share_pct": 1.8611465700422023,
      "label": null,
      "hl": null,
      "is_val": false,
      "entered": null,
      "entered_method": "baseline",
      "is_new": false
    },
    {
      "rank": 9,
      "coldkey": "5F2TtKvr8b15iUiPb1XwiNfLLRv4e1TP8EtPX6hE5AyxUGoq",
      "alpha": 46561.744500086,
      "usd": 128088.18549539731,
      "share_pct": 1.8565384852360391,
      "label": null,
      "hl": null,
      "is_val": false,
      "entered": null,
      "entered_method": "baseline",
      "is_new": false
    },
    {
      "rank": 10,
      "coldkey": "5GuRLEMgsMQsKSXQ9CjvQGpDxiMuSCcdkyQNz4nuoHURiuaC",
      "alpha": 43818.063190715,
      "usd": 120540.50522121174,
      "share_pct": 1.7471407382925015,
      "label": null,
      "hl": null,
      "is_val": false,
      "entered": null,
      "entered_method": "baseline",
      "is_new": false
    },
    {
      "rank": 11,
      "coldkey": "5C5MwSq3tZpytAnUjrrX6bskMb7Eu1nKYBMZnTxNdxfPBjmK",
      "alpha": 41244.593696191,
      "usd": 113461.06604812131,
      "share_pct": 1.6445297814123114,
      "label": null,
      "hl": null,
      "is_val": false,
      "entered": null,
      "entered_method": "baseline",
      "is_new": false
    },
    {
      "rank": 12,
      "coldkey": "5CZtgF1xChRMKXrihA62smGMvhtRCaSsyz1tRqngCJQoVL4f",
      "alpha": 32405.052056256,
      "usd": 89144.08949523054,
      "share_pct": 1.2920741459419631,
      "label": null,
      "hl": null,
      "is_val": false,
      "entered": null,
      "entered_method": "baseline",
      "is_new": false
    },
    {
      "rank": 13,
      "coldkey": "5DvLgNyXeLGj7MKHg9uAywzJk2AaaGsdPrvSqEtGpVzXaKXN",
      "alpha": 32307.494427656,
      "usd": 88875.71510842927,
      "share_pct": 1.2881842682329367,
      "label": null,
      "hl": null,
      "is_val": false,
      "entered": null,
      "entered_method": "baseline",
      "is_new": false
    },
    {
      "rank": 14,
      "coldkey": "5Gn4mB83yd6U6nPcBUQDHGBCVBxNrMmFaMj1YL8Bqns9kBNi",
      "alpha": 31307.813598952,
      "usd": 86125.66128639101,
      "share_pct": 1.2483243800056343,
      "label": null,
      "hl": null,
      "is_val": false,
      "entered": null,
      "entered_method": "baseline",
      "is_new": false
    },
    {
      "rank": 15,
      "coldkey": "5GJCurC77WmHjAXHoquwiQcKKGMsM9eJQ4q6La4M8E3xeLsb",
      "alpha": 30999.923515927,
      "usd": 85278.67665361748,
      "share_pct": 1.2360479974410299,
      "label": null,
      "hl": null,
      "is_val": false,
      "entered": "2026-07-10",
      "entered_method": "first-seen",
      "is_new": true
    },
    {
      "rank": 16,
      "coldkey": "5F85xjhaRjSjk3qX5DPPav2S6ouVrxXANaFpaznz47iPPYgb",
      "alpha": 30477.394607892,
      "usd": 83841.23524291239,
      "share_pct": 1.215213403766956,
      "label": null,
      "hl": null,
      "is_val": false,
      "entered": null,
      "entered_method": "baseline",
      "is_new": false
    },
    {
      "rank": 17,
      "coldkey": "5HihiJi6XbPhnPBKGwHMYwNnCNjXZnvQ64VTqdY4tLvUmKAq",
      "alpha": 27966.18936354,
      "usd": 76933.08077814616,
      "share_pct": 1.1150850853261067,
      "label": null,
      "hl": null,
      "is_val": false,
      "entered": null,
      "entered_method": "baseline",
      "is_new": false
    },
    {
      "rank": 18,
      "coldkey": "5EHRQUR6wdnLYiNuZ6HdahkLzSgLMxFF8gz9gBBcg5gHieJi",
      "alpha": 27902.822127726,
      "usd": 76758.76183149975,
      "share_pct": 1.1125584679655502,
      "label": null,
      "hl": null,
      "is_val": false,
      "entered": null,
      "entered_method": "baseline",
      "is_new": false
    },
    {
      "rank": 19,
      "coldkey": "5FX5ETjJ4kFeBNFVQySAU8pDmC2RoHBsJPVmkNEEA4uMTJ9v",
      "alpha": 24506.400259569,
      "usd": 67415.4367705516,
      "share_pct": 0.97713424840438,
      "label": null,
      "hl": null,
      "is_val": false,
      "entered": null,
      "entered_method": "baseline",
      "is_new": false
    },
    {
      "rank": 20,
      "coldkey": "5GR3LELy12yXmy8G9dpVS8FrCibtnd3iq97DzQKtDjcUy6XV",
      "alpha": 22606.192021575,
      "usd": 62188.09342503739,
      "share_pct": 0.9013679780106256,
      "label": null,
      "hl": null,
      "is_val": false,
      "entered": null,
      "entered_method": "baseline",
      "is_new": false
    },
    {
      "rank": 21,
      "coldkey": "5DkkkEhnc8AFC1syp6HTkmcZvpzRzf5o5MHxkgZVu1Y6BTCg",
      "alpha": 22214.079609477,
      "usd": 61109.4189055343,
      "share_pct": 0.8857334309932275,
      "label": null,
      "hl": null,
      "is_val": false,
      "entered": null,
      "entered_method": "baseline",
      "is_new": false
    },
    {
      "rank": 22,
      "coldkey": "5GQmuvvrnbhaGHMgubNSjXNULwJwr63pr4NepAg29arSfKGF",
      "alpha": 21593.972298343,
      "usd": 59403.54595879715,
      "share_pct": 0.8610081312765389,
      "label": null,
      "hl": null,
      "is_val": false,
      "entered": null,
      "entered_method": "baseline",
      "is_new": false
    },
    {
      "rank": 23,
      "coldkey": "5F1c6eSu9KcNQnbAst9ziyYRin3aMUXxMk3f3WdwwcsVpUur",
      "alpha": 21343.770115744,
      "usd": 58715.2568081182,
      "share_pct": 0.8510319161223957,
      "label": null,
      "hl": null,
      "is_val": false,
      "entered": null,
      "entered_method": "baseline",
      "is_new": false
    },
    {
      "rank": 24,
      "coldkey": "5GKDKi693xQehe27jNyyimGyfcgK6hT7rx3EuNkoWGY4skqA",
      "alpha": 20388.804372838,
      "usd": 56088.2111393532,
      "share_pct": 0.8129549352699333,
      "label": null,
      "hl": null,
      "is_val": false,
      "entered": null,
      "entered_method": "baseline",
      "is_new": false
    },
    {
      "rank": 25,
      "coldkey": "5EqQMCp1kuYirYGZhhM4nN8CCvX2zfA8ZeFqbqikDdCTT6kj",
      "alpha": 19996.26644345,
      "usd": 55008.366050788354,
      "share_pct": 0.7973034217657016,
      "label": null,
      "hl": null,
      "is_val": false,
      "entered": "2026-07-17",
      "entered_method": "first-seen",
      "is_new": true
    }
  ]
}